rsa/__init__.py
rsa/operations.py
deterministic_rsa_keygen-1.0.dist-info/LICENSE
deterministic_rsa_keygen-1.0.dist-info/METADATA
deterministic_rsa_keygen-1.0.dist-info/WHEEL
deterministic_rsa_keygen-1.0.dist-info/RECORD
